pyspark2pmml/__init__.py
pyspark2pmml/metadata.py
pyspark2pmml/xgboost.py
pyspark2pmml/ml/__init__.py
pyspark2pmml/ml/feature.py
pyspark2pmml-0.8.2.dist-info/licenses/LICENSE.txt
pyspark2pmml-0.8.2.dist-info/METADATA
pyspark2pmml-0.8.2.dist-info/WHEEL
pyspark2pmml-0.8.2.dist-info/top_level.txt
pyspark2pmml-0.8.2.dist-info/RECORD
