Metadata-Version: 2.4
Name: pyspark2pmml
Version: 0.8.2
Summary: Python library for converting Apache Spark ML pipelines to PMML
Home-page: https://github.com/jpmml/pyspark2pmml
Download-URL: https://github.com/jpmml/pyspark2pmml/archive/0.8.2.tar.gz
Author: Villu Ruusmann
Author-email: villu.ruusmann@gmail.com
License: GNU Affero General Public License (AGPL) version 3.0
Classifier: Development Status :: 5 - Production/Stable
Classifier: Operating System :: OS Independent
Classifier: Programming Language :: Python
Classifier: Intended Audience :: Developers
Classifier: Intended Audience :: Science/Research
Classifier: Topic :: Software Development
Classifier: Topic :: Scientific/Engineering
Requires-Python: >=3.6
License-File: LICENSE.txt
Requires-Dist: py4j
Dynamic: author
Dynamic: author-email
Dynamic: classifier
Dynamic: download-url
Dynamic: home-page
Dynamic: license
Dynamic: license-file
Dynamic: requires-dist
Dynamic: requires-python
Dynamic: summary
